kikicocoTest/test1.py
kikicocoTest/test2.py
kikicocoTest-0.0.0.2.dist-info/METADATA
kikicocoTest-0.0.0.2.dist-info/WHEEL
kikicocoTest-0.0.0.2.dist-info/top_level.txt
kikicocoTest-0.0.0.2.dist-info/RECORD
