Metadata-Version: 2.1
Name: kikicocoTest
Version: 0.0.0.2
Summary: My First Test Package
Home-page: UNKNOWN
Author: Martin Kang
Author-email: kangsb1518@gmail.com
License: MIT
Platform: UNKNOWN
Requires-Python: >=3
